{"cameraMode":{"drawMode":0,"name":"Shaded","section":"Shading Mode"},"sceneLighting":false,"audioPlay":false,"sceneViewState":{"m_AlwaysRefresh":false,"showFog":true,"showSkybox":false,"showFlares":true,"showImageEffects":true,"showParticleSystems":true,"showVisualEffectGraphs":true,"m_FxEnabled":true},"in2DMode":false,"pivot":{"x":0.1956050992012024,"y":-0.012743540108203888,"z":0.5876489877700806},"rotation":{"x":0.17676901817321778,"y":-0.07437021285295487,"z":-0.01331816054880619,"w":-0.9814134240150452},"size":0.8198042511940002,"orthographic":false}